README.md
setup.py
RLSolver.egg-info/PKG-INFO
RLSolver.egg-info/SOURCES.txt
RLSolver.egg-info/dependency_links.txt
RLSolver.egg-info/top_level.txt
opt_methods/__init__.py
opt_methods/branch_and_bound.py
opt_methods/cutting_plane.py
rlsolver/__init__.py
rlsolver/envs/__init__.py
rlsolver/envs/chip_design/__init__.py
rlsolver/envs/learn2optimize/__init__.py
rlsolver/envs/mimo_beamforming/__init__.py
rlsolver/envs/mimo_beamforming/baseline_mmse.py
rlsolver/envs/mimo_beamforming/baseline_unfolded_mmse_net.py
rlsolver/envs/mimo_beamforming/baseline_zf_mmse.py
rlsolver/envs/mimo_beamforming/env_mimo.py
rlsolver/envs/mimo_beamforming/env_mimo_relay.py
rlsolver/envs/mimo_beamforming/vecenv_mimo.py
rlsolver/envs/portfolio_management/__init__.py
rlsolver/envs/portfolio_management/portfolio_management.py
rlsolver/envs/quantum_circuits/__init__.py
rlsolver/envs/quantum_circuits/tn_contraction_path.py
rlsolver/envs/vehicle_routing/__init__.py
rlsolver/envs/vehicle_routing/train_attention_model_vehicle_routing.py
rlsolver/envs/vehicle_routing/train_pointer_network_vehicle_routing.py
rlsolver/envs/vehicle_routing/train_reinforce_maxcut_vehicle_routing.py
rlsolver/envs/vehicle_routing/train_s2v_dqn_maxcut_vehicle_routing.py
rlsolver/envs/vehicle_routing/vehicle_routing.py
rlsolver/envs/virtual_machine_placement/__init__.py
rlsolver/rlsolver_compressive_sensing/__init__.py
rlsolver/rlsolver_compressive_sensing/file_utils.py
rlsolver/rlsolver_compressive_sensing/train_dcs.py
rlsolver/rlsolver_learn2optimize/__init__.py
rlsolver/rlsolver_mimo_beamforming/Single_File_Demo_mimo.py
rlsolver/rlsolver_mimo_beamforming/__init__.py
rlsolver/rlsolver_mimo_beamforming/evaluator_mimo.py
rlsolver/rlsolver_mimo_beamforming/evaluator_mimo_relay.py
rlsolver/rlsolver_mimo_beamforming/net_mimo.py
rlsolver/rlsolver_mimo_beamforming/net_mimo_relay.py
rlsolver/rlsolver_mimo_beamforming/train_reinforce_mimo.py
rlsolver/rlsolver_mimo_beamforming/train_reinforce_mimo_relay.py
rlsolver/rlsolver_mimo_beamforming/train_reinforce_podracer_mimo.py
rlsolver/rlsolver_portfolio_management/__init__.py
